[
 {
  "id": "63:9/c1",
  "unit_text": "وَمَن يَفْعَلْ ذَٰلِكَ فَأُو۟لَـٰٓئِكَ هُمُ ٱلْخَـٰسِرُونَ",
  "full_ayah": "يا أيها الذين آمنوا لا تلهكم أموالكم ولا أولادكم عن ذكر الله ومن يفعل ذلك فأولئك هم الخاسرون",
  "gates": [
   "G1b:شرط-العموم"
  ],
  "candidates": [
   {
    "loc": "20:132",
    "text": "وأمر أهلك بالصلاة واصطبر عليها لا نسألك رزقا نحن نرزقك والعاقبة للتقوى"
   },
   {
    "loc": "9:23",
    "text": "يا أيها الذين آمنوا لا تتخذوا آباءكم وإخوانكم أولياء إن استحبوا الكفر على الإيمان ومن يتولهم منكم فأولئك هم الظالمون"
   },
   {
    "loc": "8:27",
    "text": "يا أيها الذين آمنوا لا تخونوا الله والرسول وتخونوا أماناتكم وأنتم تعلمون"
   },
   {
    "loc": "58:17",
    "text": "لن تغني عنهم أموالهم ولا أولادهم من الله شيئا أولئك أصحاب النار هم فيها خالدون"
   },
   {
    "loc": "58:19",
    "text": "استحوذ عليهم الشيطان فأنساهم ذكر الله أولئك حزب الشيطان ألا إن حزب الشيطان هم الخاسرون"
   },
   {
    "loc": "51:55",
    "text": "وذكر فإن الذكرى تنفع المؤمنين"
   },
   {
    "loc": "31:33",
    "text": "يا أيها الناس اتقوا ربكم واخشوا يوما لا يجزي والد عن ولده ولا مولود هو جاز عن والده شيئا إن وعد الله حق فلا تغرنكم الحياة الدنيا ولا يغرنكم بالله الغرور"
   },
   {
    "loc": "13:28",
    "text": "الذين آمنوا وتطمئن قلوبهم بذكر الله ألا بذكر الله تطمئن القلوب"
   },
   {
    "loc": "3:149",
    "text": "يا أيها الذين آمنوا إن تطيعوا الذين كفروا يردوكم على أعقابكم فتنقلبوا خاسرين"
   },
   {
    "loc": "3:130",
    "text": "يا أيها الذين آمنوا لا تأكلوا الربا أضعافا مضاعفة واتقوا الله لعلكم تفلحون"
   },
   {
    "loc": "5:105",
    "text": "يا أيها الذين آمنوا عليكم أنفسكم لا يضركم من ضل إذا اهتديتم إلى الله مرجعكم جميعا فينبئكم بما كنتم تعملون"
   },
   {
    "loc": "2:278",
    "text": "يا أيها الذين آمنوا اتقوا الله وذروا ما بقي من الربا إن كنتم مؤمنين"
   },
   {
    "loc": "10:95",
    "text": "ولا تكونن من الذين كذبوا بآيات الله فتكون من الخاسرين"
   },
   {
    "loc": "9:55",
    "text": "فلا تعجبك أموالهم ولا أولادهم إنما يريد الله ليعذبهم بها في الحياة الدنيا وتزهق أنفسهم وهم كافرون"
   },
   {
    "loc": "18:30",
    "text": "إن الذين آمنوا وعملوا الصالحات إنا لا نضيع أجر من أحسن عملا"
   },
   {
    "loc": "39:65",
    "text": "ولقد أوحي إليك وإلى الذين من قبلك لئن أشركت ليحبطن عملك ولتكونن من الخاسرين"
   },
   {
    "loc": "64:16",
    "text": "فاتقوا الله ما استطعتم واسمعوا وأطيعوا وأنفقوا خيرا لأنفسكم ومن يوق شح نفسه فأولئك هم المفلحون"
   },
   {
    "loc": "9:85",
    "text": "ولا تعجبك أموالهم وأولادهم إنما يريد الله أن يعذبهم بها في الدنيا وتزهق أنفسهم وهم كافرون"
   },
   {
    "loc": "9:119",
    "text": "يا أيها الذين آمنوا اتقوا الله وكونوا مع الصادقين"
   },
   {
    "loc": "10:106",
    "text": "ولا تدع من دون الله ما لا ينفعك ولا يضرك فإن فعلت فإنك إذا من الظالمين"
   },
   {
    "loc": "7:178",
    "text": "من يهد الله فهو المهتدي ومن يضلل فأولئك هم الخاسرون"
   },
   {
    "loc": "24:52",
    "text": "ومن يطع الله ورسوله ويخش الله ويتقه فأولئك هم الفائزون"
   },
   {
    "loc": "42:36",
    "text": "فما أوتيتم من شيء فمتاع الحياة الدنيا وما عند الله خير وأبقى للذين آمنوا وعلى ربهم يتوكلون"
   },
   {
    "loc": "52:21",
    "text": "والذين آمنوا واتبعتهم ذريتهم بإيمان ألحقنا بهم ذريتهم وما ألتناهم من عملهم من شيء كل امرئ بما كسب رهين"
   },
   {
    "loc": "7:51",
    "text": "الذين اتخذوا دينهم لهوا ولعبا وغرتهم الحياة الدنيا فاليوم ننساهم كما نسوا لقاء يومهم هذا وما كانوا بآياتنا يجحدون"
   },
   {
    "loc": "18:28",
    "text": "واصبر نفسك مع الذين يدعون ربهم بالغداة والعشي يريدون وجهه ولا تعد عيناك عنهم تريد زينة الحياة الدنيا ولا تطع من أغفلنا قلبه عن ذكرنا واتبع هواه وكان أمره فرطا"
   },
   {
    "loc": "22:77",
    "text": "يا أيها الذين آمنوا اركعوا واسجدوا واعبدوا ربكم وافعلوا الخير لعلكم تفلحون"
   },
   {
    "loc": "3:102",
    "text": "يا أيها الذين آمنوا اتقوا الله حق تقاته ولا تموتن إلا وأنتم مسلمون"
   },
   {
    "loc": "60:3",
    "text": "لن تنفعكم أرحامكم ولا أولادكم يوم القيامة يفصل بينكم والله بما تعملون بصير"
   },
   {
    "loc": "61:11",
    "text": "تؤمنون بالله ورسوله وتجاهدون في سبيل الله بأموالكم وأنفسكم ذلكم خير لكم إن كنتم تعلمون"
   },
   {
    "loc": "17:22",
    "text": "لا تجعل مع الله إلها آخر فتقعد مذموما مخذولا"
   },
   {
    "loc": "2:262",
    "text": "الذين ينفقون أموالهم في سبيل الله ثم لا يتبعون ما أنفقوا منا ولا أذى لهم أجرهم عند ربهم ولا خوف عليهم ولا هم يحزنون"
   },
   {
    "loc": "4:36",
    "text": "واعبدوا الله ولا تشركوا به شيئا وبالوالدين إحسانا وبذي القربى واليتامى والمساكين والجار ذي القربى والجار الجنب والصاحب بالجنب وابن السبيل وما ملكت أيمانكم إن الله لا يحب من كان مختالا فخورا"
   },
   {
    "loc": "3:200",
    "text": "يا أيها الذين آمنوا اصبروا وصابروا ورابطوا واتقوا الله لعلكم تفلحون"
   },
   {
    "loc": "33:70",
    "text": "يا أيها الذين آمنوا اتقوا الله وقولوا قولا سديدا"
   },
   {
    "loc": "35:5",
    "text": "يا أيها الناس إن وعد الله حق فلا تغرنكم الحياة الدنيا ولا يغرنكم بالله الغرور"
   },
   {
    "loc": "6:69",
    "text": "وما على الذين يتقون من حسابهم من شيء ولكن ذكرى لعلهم يتقون"
   },
   {
    "loc": "16:90",
    "text": "إن الله يأمر بالعدل والإحسان وإيتاء ذي القربى وينهى عن الفحشاء والمنكر والبغي يعظكم لعلكم تذكرون"
   },
   {
    "loc": "28:77",
    "text": "وابتغ فيما آتاك الله الدار الآخرة ولا تنس نصيبك من الدنيا وأحسن كما أحسن الله إليك ولا تبغ الفساد في الأرض إن الله لا يحب المفسدين"
   },
   {
    "loc": "6:32",
    "text": "وما الحياة الدنيا إلا لعب ولهو وللدار الآخرة خير للذين يتقون أفلا تعقلون"
   },
   {
    "loc": "6:70",
    "text": "وذر الذين اتخذوا دينهم لعبا ولهوا وغرتهم الحياة الدنيا وذكر به أن تبسل نفس بما كسبت ليس لها من دون الله ولي ولا شفيع وإن تعدل كل عدل لا يؤخذ منها أولئك الذين أبسلوا بما كسبوا لهم شراب من حميم وعذاب أليم بما كانوا يكفرون"
   },
   {
    "loc": "15:3",
    "text": "ذرهم يأكلوا ويتمتعوا ويلههم الأمل فسوف يعلمون"
   },
   {
    "loc": "21:3",
    "text": "لاهية قلوبهم وأسروا النجوى الذين ظلموا هل هذا إلا بشر مثلكم أفتأتون السحر وأنتم تبصرون"
   },
   {
    "loc": "21:17",
    "text": "لو أردنا أن نتخذ لهوا لاتخذناه من لدنا إن كنا فاعلين"
   },
   {
    "loc": "24:37",
    "text": "رجال لا تلهيهم تجارة ولا بيع عن ذكر الله وإقام الصلاة وإيتاء الزكاة يخافون يوما تتقلب فيه القلوب والأبصار"
   },
   {
    "loc": "29:64",
    "text": "وما هذه الحياة الدنيا إلا لهو ولعب وإن الدار الآخرة لهي الحيوان لو كانوا يعلمون"
   },
   {
    "loc": "31:6",
    "text": "ومن الناس من يشتري لهو الحديث ليضل عن سبيل الله بغير علم ويتخذها هزوا أولئك لهم عذاب مهين"
   },
   {
    "loc": "47:36",
    "text": "إنما الحياة الدنيا لعب ولهو وإن تؤمنوا وتتقوا يؤتكم أجوركم ولا يسألكم أموالكم"
   },
   {
    "loc": "57:20",
    "text": "اعلموا أنما الحياة الدنيا لعب ولهو وزينة وتفاخر بينكم وتكاثر في الأموال والأولاد كمثل غيث أعجب الكفار نباته ثم يهيج فتراه مصفرا ثم يكون حطاما وفي الآخرة عذاب شديد ومغفرة من الله ورضوان وما الحياة الدنيا إلا متاع الغرور"
   },
   {
    "loc": "80:10",
    "text": "فأنت عنه تلهى"
   },
   {
    "loc": "2:155",
    "text": "ولنبلونكم بشيء من الخوف والجوع ونقص من الأموال والأنفس والثمرات وبشر الصابرين"
   },
   {
    "loc": "2:177",
    "text": "ليس البر أن تولوا وجوهكم قبل المشرق والمغرب ولكن البر من آمن بالله واليوم الآخر والملائكة والكتاب والنبيين وآتى المال على حبه ذوي القربى واليتامى والمساكين وابن السبيل والسائلين وفي الرقاب وأقام الصلاة وآتى الزكاة والموفون بعهدهم إذا عاهدوا والصابرين في البأساء والضراء وحين البأس أولئك الذين صدقوا وأولئك هم المتقون"
   },
   {
    "loc": "2:188",
    "text": "ولا تأكلوا أموالكم بينكم بالباطل وتدلوا بها إلى الحكام لتأكلوا فريقا من أموال الناس بالإثم وأنتم تعلمون"
   },
   {
    "loc": "2:247",
    "text": "وقال لهم نبيهم إن الله قد بعث لكم طالوت ملكا قالوا أنى يكون له الملك علينا ونحن أحق بالملك منه ولم يؤت سعة من المال قال إن الله اصطفاه عليكم وزاده بسطة في العلم والجسم والله يؤتي ملكه من يشاء والله واسع عليم"
   }
  ]
 },
 {
  "id": "63:10/aya",
  "unit_text": "وَأَنفِقُوا۟ مِن مَّا رَزَقْنَـٰكُم مِّن قَبْلِ أَن يَأْتِىَ أَحَدَكُمُ ٱلْمَوْتُ فَيَقُولَ رَبِّ لَوْلَآ أَخَّرْتَنِىٓ إِلَىٰٓ أَجَلٍ قَرِيبٍ فَأَصَّدَّقَ وَأَكُن مِّنَ ٱلصَّـٰلِحِينَ",
  "full_ayah": "وأنفقوا من ما رزقناكم من قبل أن يأتي أحدكم الموت فيقول رب لولا أخرتني إلى أجل قريب فأصدق وأكن من الصالحين",
  "gates": [
   "G1h:أمر-جمعي"
  ],
  "candidates": [
   {
    "loc": "42:20",
    "text": "من كان يريد حرث الآخرة نزد له في حرثه ومن كان يريد حرث الدنيا نؤته منها وما له في الآخرة من نصيب"
   },
   {
    "loc": "2:215",
    "text": "يسألونك ماذا ينفقون قل ما أنفقتم من خير فللوالدين والأقربين واليتامى والمساكين وابن السبيل وما تفعلوا من خير فإن الله به عليم"
   },
   {
    "loc": "28:77",
    "text": "وابتغ فيما آتاك الله الدار الآخرة ولا تنس نصيبك من الدنيا وأحسن كما أحسن الله إليك ولا تبغ الفساد في الأرض إن الله لا يحب المفسدين"
   },
   {
    "loc": "36:47",
    "text": "وإذا قيل لهم أنفقوا مما رزقكم الله قال الذين كفروا للذين آمنوا أنطعم من لو يشاء الله أطعمه إن أنتم إلا في ضلال مبين"
   },
   {
    "loc": "2:281",
    "text": "واتقوا يوما ترجعون فيه إلى الله ثم توفى كل نفس ما كسبت وهم لا يظلمون"
   },
   {
    "loc": "59:18",
    "text": "يا أيها الذين آمنوا اتقوا الله ولتنظر نفس ما قدمت لغد واتقوا الله إن الله خبير بما تعملون"
   },
   {
    "loc": "38:16",
    "text": "وقالوا ربنا عجل لنا قطنا قبل يوم الحساب"
   },
   {
    "loc": "3:157",
    "text": "ولئن قتلتم في سبيل الله أو متم لمغفرة من الله ورحمة خير مما يجمعون"
   },
   {
    "loc": "57:7",
    "text": "آمنوا بالله ورسوله وأنفقوا مما جعلكم مستخلفين فيه فالذين آمنوا منكم وأنفقوا لهم أجر كبير"
   },
   {
    "loc": "2:110",
    "text": "وأقيموا الصلاة وآتوا الزكاة وما تقدموا لأنفسكم من خير تجدوه عند الله إن الله بما تعملون بصير"
   },
   {
    "loc": "16:96",
    "text": "ما عندكم ينفد وما عند الله باق ولنجزين الذين صبروا أجرهم بأحسن ما كانوا يعملون"
   },
   {
    "loc": "2:262",
    "text": "الذين ينفقون أموالهم في سبيل الله ثم لا يتبعون ما أنفقوا منا ولا أذى لهم أجرهم عند ربهم ولا خوف عليهم ولا هم يحزنون"
   },
   {
    "loc": "11:3",
    "text": "وأن استغفروا ربكم ثم توبوا إليه يمتعكم متاعا حسنا إلى أجل مسمى ويؤت كل ذي فضل فضله وإن تولوا فإني أخاف عليكم عذاب يوم كبير"
   },
   {
    "loc": "2:245",
    "text": "من ذا الذي يقرض الله قرضا حسنا فيضاعفه له أضعافا كثيرة والله يقبض ويبسط وإليه ترجعون"
   },
   {
    "loc": "47:38",
    "text": "ها أنتم هؤلاء تدعون لتنفقوا في سبيل الله فمنكم من يبخل ومن يبخل فإنما يبخل عن نفسه والله الغني وأنتم الفقراء وإن تتولوا يستبدل قوما غيركم ثم لا يكونوا أمثالكم"
   },
   {
    "loc": "2:180",
    "text": "كتب عليكم إذا حضر أحدكم الموت إن ترك خيرا الوصية للوالدين والأقربين بالمعروف حقا على المتقين"
   },
   {
    "loc": "22:58",
    "text": "والذين هاجروا في سبيل الله ثم قتلوا أو ماتوا ليرزقنهم الله رزقا حسنا وإن الله لهو خير الرازقين"
   },
   {
    "loc": "9:38",
    "text": "يا أيها الذين آمنوا ما لكم إذا قيل لكم انفروا في سبيل الله اثاقلتم إلى الأرض أرضيتم بالحياة الدنيا من الآخرة فما متاع الحياة الدنيا في الآخرة إلا قليل"
   },
   {
    "loc": "71:4",
    "text": "يغفر لكم من ذنوبكم ويؤخركم إلى أجل مسمى إن أجل الله إذا جاء لا يؤخر لو كنتم تعلمون"
   },
   {
    "loc": "6:58",
    "text": "قل لو أن عندي ما تستعجلون به لقضي الأمر بيني وبينكم والله أعلم بالظالمين"
   },
   {
    "loc": "64:17",
    "text": "إن تقرضوا الله قرضا حسنا يضاعفه لكم ويغفر لكم والله شكور حليم"
   },
   {
    "loc": "14:51",
    "text": "ليجزي الله كل نفس ما كسبت إن الله سريع الحساب"
   },
   {
    "loc": "9:41",
    "text": "انفروا خفافا وثقالا وجاهدوا بأموالكم وأنفسكم في سبيل الله ذلكم خير لكم إن كنتم تعلمون"
   },
   {
    "loc": "10:49",
    "text": "قل لا أملك لنفسي ضرا ولا نفعا إلا ما شاء الله لكل أمة أجل إذا جاء أجلهم فلا يستأخرون ساعة ولا يستقدمون"
   },
   {
    "loc": "3:185",
    "text": "كل نفس ذائقة الموت وإنما توفون أجوركم يوم القيامة فمن زحزح عن النار وأدخل الجنة فقد فاز وما الحياة الدنيا إلا متاع الغرور"
   },
   {
    "loc": "2:3",
    "text": "الذين يؤمنون بالغيب ويقيمون الصلاة ومما رزقناهم ينفقون"
   },
   {
    "loc": "2:265",
    "text": "ومثل الذين ينفقون أموالهم ابتغاء مرضات الله وتثبيتا من أنفسهم كمثل جنة بربوة أصابها وابل فآتت أكلها ضعفين فإن لم يصبها وابل فطل والله بما تعملون بصير"
   },
   {
    "loc": "8:3",
    "text": "الذين يقيمون الصلاة ومما رزقناهم ينفقون"
   },
   {
    "loc": "24:22",
    "text": "ولا يأتل أولو الفضل منكم والسعة أن يؤتوا أولي القربى والمساكين والمهاجرين في سبيل الله وليعفوا وليصفحوا ألا تحبون أن يغفر الله لكم والله غفور رحيم"
   },
   {
    "loc": "92:18",
    "text": "الذي يؤتي ماله يتزكى"
   },
   {
    "loc": "57:18",
    "text": "إن المصدقين والمصدقات وأقرضوا الله قرضا حسنا يضاعف لهم ولهم أجر كريم"
   },
   {
    "loc": "39:57",
    "text": "أو تقول لو أن الله هداني لكنت من المتقين"
   },
   {
    "loc": "34:4",
    "text": "ليجزي الذين آمنوا وعملوا الصالحات أولئك لهم مغفرة ورزق كريم"
   },
   {
    "loc": "35:29",
    "text": "إن الذين يتلون كتاب الله وأقاموا الصلاة وأنفقوا مما رزقناهم سرا وعلانية يرجون تجارة لن تبور"
   },
   {
    "loc": "13:22",
    "text": "والذين صبروا ابتغاء وجه ربهم وأقاموا الصلاة وأنفقوا مما رزقناهم سرا وعلانية ويدرءون بالحسنة السيئة أولئك لهم عقبى الدار"
   },
   {
    "loc": "29:5",
    "text": "من كان يرجو لقاء الله فإن أجل الله لآت وهو السميع العليم"
   },
   {
    "loc": "39:47",
    "text": "ولو أن للذين ظلموا ما في الأرض جميعا ومثله معه لافتدوا به من سوء العذاب يوم القيامة وبدا لهم من الله ما لم يكونوا يحتسبون"
   },
   {
    "loc": "17:19",
    "text": "ومن أراد الآخرة وسعى لها سعيها وهو مؤمن فأولئك كان سعيهم مشكورا"
   },
   {
    "loc": "2:272",
    "text": "ليس عليك هداهم ولكن الله يهدي من يشاء وما تنفقوا من خير فلأنفسكم وما تنفقون إلا ابتغاء وجه الله وما تنفقوا من خير يوف إليكم وأنتم لا تظلمون"
   },
   {
    "loc": "2:219",
    "text": "يسألونك عن الخمر والميسر قل فيهما إثم كبير ومنافع للناس وإثمهما أكبر من نفعهما ويسألونك ماذا ينفقون قل العفو كذلك يبين الله لكم الآيات لعلكم تتفكرون"
   },
   {
    "loc": "2:261",
    "text": "مثل الذين ينفقون أموالهم في سبيل الله كمثل حبة أنبتت سبع سنابل في كل سنبلة مائة حبة والله يضاعف لمن يشاء والله واسع عليم"
   },
   {
    "loc": "2:270",
    "text": "وما أنفقتم من نفقة أو نذرتم من نذر فإن الله يعلمه وما للظالمين من أنصار"
   },
   {
    "loc": "2:273",
    "text": "للفقراء الذين أحصروا في سبيل الله لا يستطيعون ضربا في الأرض يحسبهم الجاهل أغنياء من التعفف تعرفهم بسيماهم لا يسألون الناس إلحافا وما تنفقوا من خير فإن الله به عليم"
   },
   {
    "loc": "3:17",
    "text": "الصابرين والصادقين والقانتين والمنفقين والمستغفرين بالأسحار"
   },
   {
    "loc": "3:117",
    "text": "مثل ما ينفقون في هذه الحياة الدنيا كمثل ريح فيها صر أصابت حرث قوم ظلموا أنفسهم فأهلكته وما ظلمهم الله ولكن أنفسهم يظلمون"
   },
   {
    "loc": "3:134",
    "text": "الذين ينفقون في السراء والضراء والكاظمين الغيظ والعافين عن الناس والله يحب المحسنين"
   },
   {
    "loc": "3:167",
    "text": "وليعلم الذين نافقوا وقيل لهم تعالوا قاتلوا في سبيل الله أو ادفعوا قالوا لو نعلم قتالا لاتبعناكم هم للكفر يومئذ أقرب منهم للإيمان يقولون بأفواههم ما ليس في قلوبهم والله أعلم بما يكتمون"
   },
   {
    "loc": "4:34",
    "text": "الرجال قوامون على النساء بما فضل الله بعضهم على بعض وبما أنفقوا من أموالهم فالصالحات قانتات حافظات للغيب بما حفظ الله واللاتي تخافون نشوزهن فعظوهن واهجروهن في المضاجع واضربوهن فإن أطعنكم فلا تبغوا عليهن سبيلا إن الله كان عليا كبيرا"
   },
   {
    "loc": "4:38",
    "text": "والذين ينفقون أموالهم رئاء الناس ولا يؤمنون بالله ولا باليوم الآخر ومن يكن الشيطان له قرينا فساء قرينا"
   },
   {
    "loc": "4:61",
    "text": "وإذا قيل لهم تعالوا إلى ما أنزل الله وإلى الرسول رأيت المنافقين يصدون عنك صدودا"
   },
   {
    "loc": "4:88",
    "text": "فما لكم في المنافقين فئتين والله أركسهم بما كسبوا أتريدون أن تهدوا من أضل الله ومن يضلل الله فلن تجد له سبيلا"
   },
   {
    "loc": "4:138",
    "text": "بشر المنافقين بأن لهم عذابا أليما"
   },
   {
    "loc": "4:140",
    "text": "وقد نزل عليكم في الكتاب أن إذا سمعتم آيات الله يكفر بها ويستهزأ بها فلا تقعدوا معهم حتى يخوضوا في حديث غيره إنكم إذا مثلهم إن الله جامع المنافقين والكافرين في جهنم جميعا"
   }
  ]
 }
]