[{"id":"68:10/aya","unit_text":"وَلَا تُطِعْ كُلَّ حَلَّافٍ مَّهِينٍ","full_ayah":"وَلَا تُطِعْ كُلَّ حَلَّافٍ مَّهِينٍ","gates":["G1a:كل/جميع","G1c:نفي+نكرة"],"candidates":[{"loc":"26:151","text":"وَلَا تُطِيعُوٓا۟ أَمْرَ ٱلْمُسْرِفِينَ"},{"loc":"73:10","text":"وَٱصْبِرْ عَلَىٰ مَا يَقُولُونَ وَٱهْجُرْهُمْ هَجْرًا جَمِيلًا"},{"loc":"33:48","text":"وَلَا تُطِعِ ٱلْكَـٰفِرِينَ وَٱلْمُنَـٰفِقِينَ وَدَعْ أَذَىٰهُمْ وَتَوَكَّلْ عَلَى ٱللَّهِ ۚ وَكَفَىٰ بِٱللَّهِ وَكِيلًا"},{"loc":"58:16","text":"ٱتَّخَذُوٓا۟ أَيْمَـٰنَهُمْ جُنَّةً فَصَدُّوا۟ عَن سَبِيلِ ٱللَّهِ فَلَهُمْ عَذَابٌ مُّهِينٌ"},{"loc":"26:223","text":"يُلْقُونَ ٱلسَّمْعَ وَأَكْثَرُهُمْ كَـٰذِبُونَ"},{"loc":"26:108","text":"فَٱتَّقُوا۟ ٱللَّهَ وَأَطِيعُونِ"},{"loc":"26:126","text":"فَٱتَّقُوا۟ ٱللَّهَ وَأَطِيعُونِ"},{"loc":"26:131","text":"فَٱتَّقُوا۟ ٱللَّهَ وَأَطِيعُونِ"},{"loc":"26:144","text":"فَٱتَّقُوا۟ ٱللَّهَ وَأَطِيعُونِ"},{"loc":"26:150","text":"فَٱتَّقُوا۟ ٱللَّهَ وَأَطِيعُونِ"},{"loc":"26:163","text":"فَٱتَّقُوا۟ ٱللَّهَ وَأَطِيعُونِ"},{"loc":"26:179","text":"فَٱتَّقُوا۟ ٱللَّهَ وَأَطِيعُونِ"},{"loc":"6:116","text":"وَإِن تُطِعْ أَكْثَرَ مَن فِى ٱلْأَرْضِ يُضِلُّوكَ عَن سَبِيلِ ٱللَّهِ ۚ إِن يَتَّبِعُونَ إِلَّا ٱلظَّنَّ وَإِنْ هُمْ إِلَّا يَخْرُصُونَ"},{"loc":"9:95","text":"سَيَحْلِفُونَ بِٱللَّهِ لَكُمْ إِذَا ٱنقَلَبْتُمْ إِلَيْهِمْ لِتُعْرِضُوا۟ عَنْهُمْ ۖ فَأَعْرِضُوا۟ عَنْهُمْ ۖ إِنَّهُمْ رِجْسٌ ۖ وَمَأْوَىٰهُمْ جَهَنَّمُ جَزَآءًۢ بِمَا كَانُوا۟ يَكْسِبُونَ"},{"loc":"9:96","text":"يَحْلِفُونَ لَكُمْ لِتَرْضَوْا۟ عَنْهُمْ ۖ فَإِن تَرْضَوْا۟ عَنْهُمْ فَإِنَّ ٱللَّهَ لَا يَرْضَىٰ عَنِ ٱلْقَوْمِ ٱلْفَـٰسِقِينَ"},{"loc":"2:147","text":"ٱلْحَقُّ مِن رَّبِّكَ ۖ فَلَا تَكُونَنَّ مِنَ ٱلْمُمْتَرِينَ"},{"loc":"24:53","text":"۞ وَأَقْسَمُوا۟ بِٱللَّهِ جَهْدَ أَيْمَـٰنِهِمْ لَئِنْ أَمَرْتَهُمْ لَيَخْرُجُنَّ ۖ قُل لَّا تُقْسِمُوا۟ ۖ طَاعَةٌ مَّعْرُوفَةٌ ۚ إِنَّ ٱللَّهَ خَبِيرٌۢ بِمَا تَعْمَلُونَ"},{"loc":"23:3","text":"وَٱلَّذِينَ هُمْ عَنِ ٱللَّغْوِ مُعْرِضُونَ"},{"loc":"7:199","text":"خُذِ ٱلْعَفْوَ وَأْمُرْ بِٱلْعُرْفِ وَأَعْرِضْ عَنِ ٱلْجَـٰهِلِينَ"},{"loc":"93:10","text":"وَأَمَّا ٱلسَّآئِلَ فَلَا تَنْهَرْ"},{"loc":"74:5","text":"وَٱلرُّجْزَ فَٱهْجُرْ"},{"loc":"72:4","text":"وَأَنَّهُۥ كَانَ يَقُولُ سَفِيهُنَا عَلَى ٱللَّهِ شَطَطًا"},{"loc":"108:3","text":"إِنَّ شَانِئَكَ هُوَ ٱلْأَبْتَرُ"},{"loc":"26:101","text":"وَلَا صَدِيقٍ حَمِيمٍ"},{"loc":"50:25","text":"مَّنَّاعٍ لِّلْخَيْرِ مُعْتَدٍ مُّرِيبٍ"},{"loc":"24:8","text":"وَيَدْرَؤُا۟ عَنْهَا ٱلْعَذَابَ أَن تَشْهَدَ أَرْبَعَ شَهَـٰدَٰتٍۭ بِٱللَّهِ ۙ إِنَّهُۥ لَمِنَ ٱلْكَـٰذِبِينَ"},{"loc":"14:26","text":"وَمَثَلُ كَلِمَةٍ خَبِيثَةٍ كَشَجَرَةٍ خَبِيثَةٍ ٱجْتُثَّتْ مِن فَوْقِ ٱلْأَرْضِ مَا لَهَا مِن قَرَارٍ"},{"loc":"17:29","text":"وَلَا تَجْعَلْ يَدَكَ مَغْلُولَةً إِلَىٰ عُنُقِكَ وَلَا تَبْسُطْهَا كُلَّ ٱلْبَسْطِ فَتَقْعُدَ مَلُومًا مَّحْسُورًا"},{"loc":"31:19","text":"وَٱقْصِدْ فِى مَشْيِكَ وَٱغْضُضْ مِن صَوْتِكَ ۚ إِنَّ أَنكَرَ ٱلْأَصْوَٰتِ لَصَوْتُ ٱلْحَمِيرِ"},{"loc":"9:42","text":"لَوْ كَانَ عَرَضًا قَرِيبًا وَسَفَرًا قَاصِدًا لَّٱتَّبَعُوكَ وَلَـٰكِنۢ بَعُدَتْ عَلَيْهِمُ ٱلشُّقَّةُ ۚ وَسَيَحْلِفُونَ بِٱللَّهِ لَوِ ٱسْتَطَعْنَا لَخَرَجْنَا مَعَكُمْ يُهْلِكُونَ أَنفُسَهُمْ وَٱللَّهُ يَعْلَمُ إِنَّهُمْ لَكَـٰذِبُونَ"},{"loc":"2:158","text":"۞ إِنَّ ٱلصَّفَا وَٱلْمَرْوَةَ مِن شَعَآئِرِ ٱللَّهِ ۖ فَمَنْ حَجَّ ٱلْبَيْتَ أَوِ ٱعْتَمَرَ فَلَا جُنَاحَ عَلَيْهِ أَن يَطَّوَّفَ بِهِمَا ۚ وَمَن تَطَوَّعَ خَيْرًا فَإِنَّ ٱللَّهَ شَاكِرٌ عَلِيمٌ"},{"loc":"2:184","text":"أَيَّامًا مَّعْدُودَٰتٍ ۚ فَمَن كَانَ مِنكُم مَّرِيضًا أَوْ عَلَىٰ سَفَرٍ فَعِدَّةٌ مِّنْ أَيَّامٍ أُخَرَ ۚ وَعَلَى ٱلَّذِينَ يُطِيقُونَهُۥ فِدْيَةٌ طَعَامُ مِسْكِينٍ ۖ فَمَن تَطَوَّعَ خَيْرًا فَهُوَ خَيْرٌ لَّهُۥ ۚ وَأَن تَصُومُوا۟ خَيْرٌ لَّكُمْ ۖ إِن كُنتُمْ تَعْلَمُونَ"}]},{"id":"68:22/aya","unit_text":"أَنِ ٱغْدُوا۟ عَلَىٰ حَرْثِكُمْ إِن كُنتُمْ صَـٰرِمِينَ","full_ayah":"أَنِ ٱغْدُوا۟ عَلَىٰ حَرْثِكُمْ إِن كُنتُمْ صَـٰرِمِينَ","gates":["G1h:أمر-جمعي"],"candidates":[{"loc":"56:63","text":"أَفَرَءَيْتُم مَّا تَحْرُثُونَ"},{"loc":"42:20","text":"مَن كَانَ يُرِيدُ حَرْثَ ٱلْـَٔاخِرَةِ نَزِدْ لَهُۥ فِى حَرْثِهِۦ ۖ وَمَن كَانَ يُرِيدُ حَرْثَ ٱلدُّنْيَا نُؤْتِهِۦ مِنْهَا وَمَا لَهُۥ فِى ٱلْـَٔاخِرَةِ مِن نَّصِيبٍ"},{"loc":"68:25","text":"وَغَدَوْا۟ عَلَىٰ حَرْدٍ قَـٰدِرِينَ"},{"loc":"39:39","text":"قُلْ يَـٰقَوْمِ ٱعْمَلُوا۟ عَلَىٰ مَكَانَتِكُمْ إِنِّى عَـٰمِلٌ ۖ فَسَوْفَ تَعْلَمُونَ"},{"loc":"6:135","text":"قُلْ يَـٰقَوْمِ ٱعْمَلُوا۟ عَلَىٰ مَكَانَتِكُمْ إِنِّى عَامِلٌ ۖ فَسَوْفَ تَعْلَمُونَ مَن تَكُونُ لَهُۥ عَـٰقِبَةُ ٱلدَّارِ ۗ إِنَّهُۥ لَا يُفْلِحُ ٱلظَّـٰلِمُونَ"},{"loc":"74:34","text":"وَٱلصُّبْحِ إِذَآ أَسْفَرَ"},{"loc":"2:223","text":"نِسَآؤُكُمْ حَرْثٌ لَّكُمْ فَأْتُوا۟ حَرْثَكُمْ أَنَّىٰ شِئْتُمْ ۖ وَقَدِّمُوا۟ لِأَنفُسِكُمْ ۚ وَٱتَّقُوا۟ ٱللَّهَ وَٱعْلَمُوٓا۟ أَنَّكُم مُّلَـٰقُوهُ ۗ وَبَشِّرِ ٱلْمُؤْمِنِينَ"},{"loc":"80:24","text":"فَلْيَنظُرِ ٱلْإِنسَـٰنُ إِلَىٰ طَعَامِهِۦٓ"},{"loc":"37:61","text":"لِمِثْلِ هَـٰذَا فَلْيَعْمَلِ ٱلْعَـٰمِلُونَ"},{"loc":"20:64","text":"فَأَجْمِعُوا۟ كَيْدَكُمْ ثُمَّ ٱئْتُوا۟ صَفًّا ۚ وَقَدْ أَفْلَحَ ٱلْيَوْمَ مَنِ ٱسْتَعْلَىٰ"},{"loc":"55:8","text":"أَلَّا تَطْغَوْا۟ فِى ٱلْمِيزَانِ"},{"loc":"18:23","text":"وَلَا تَقُولَنَّ لِشَا۟ىْءٍ إِنِّى فَاعِلٌ ذَٰلِكَ غَدًا"},{"loc":"53:39","text":"وَأَن لَّيْسَ لِلْإِنسَـٰنِ إِلَّا مَا سَعَىٰ"},{"loc":"37:39","text":"وَمَا تُجْزَوْنَ إِلَّا مَا كُنتُمْ تَعْمَلُونَ"},{"loc":"34:11","text":"أَنِ ٱعْمَلْ سَـٰبِغَـٰتٍ وَقَدِّرْ فِى ٱلسَّرْدِ ۖ وَٱعْمَلُوا۟ صَـٰلِحًا ۖ إِنِّى بِمَا تَعْمَلُونَ بَصِيرٌ"},{"loc":"69:23","text":"قُطُوفُهَا دَانِيَةٌ"},{"loc":"39:55","text":"وَٱتَّبِعُوٓا۟ أَحْسَنَ مَآ أُنزِلَ إِلَيْكُم مِّن رَّبِّكُم مِّن قَبْلِ أَن يَأْتِيَكُمُ ٱلْعَذَابُ بَغْتَةً وَأَنتُمْ لَا تَشْعُرُونَ"},{"loc":"12:47","text":"قَالَ تَزْرَعُونَ سَبْعَ سِنِينَ دَأَبًا فَمَا حَصَدتُّمْ فَذَرُوهُ فِى سُنۢبُلِهِۦٓ إِلَّا قَلِيلًا مِّمَّا تَأْكُلُونَ"},{"loc":"11:121","text":"وَقُل لِّلَّذِينَ لَا يُؤْمِنُونَ ٱعْمَلُوا۟ عَلَىٰ مَكَانَتِكُمْ إِنَّا عَـٰمِلُونَ"},{"loc":"3:121","text":"وَإِذْ غَدَوْتَ مِنْ أَهْلِكَ تُبَوِّئُ ٱلْمُؤْمِنِينَ مَقَـٰعِدَ لِلْقِتَالِ ۗ وَٱللَّهُ سَمِيعٌ عَلِيمٌ"},{"loc":"6:52","text":"وَلَا تَطْرُدِ ٱلَّذِينَ يَدْعُونَ رَبَّهُم بِٱلْغَدَوٰةِ وَٱلْعَشِىِّ يُرِيدُونَ وَجْهَهُۥ ۖ مَا عَلَيْكَ مِنْ حِسَابِهِم مِّن شَىْءٍ وَمَا مِنْ حِسَابِكَ عَلَيْهِم مِّن شَىْءٍ فَتَطْرُدَهُمْ فَتَكُونَ مِنَ ٱلظَّـٰلِمِينَ"},{"loc":"7:205","text":"وَٱذْكُر رَّبَّكَ فِى نَفْسِكَ تَضَرُّعًا وَخِيفَةً وَدُونَ ٱلْجَهْرِ مِنَ ٱلْقَوْلِ بِٱلْغُدُوِّ وَٱلْـَٔاصَالِ وَلَا تَكُن مِّنَ ٱلْغَـٰفِلِينَ"},{"loc":"12:12","text":"أَرْسِلْهُ مَعَنَا غَدًا يَرْتَعْ وَيَلْعَبْ وَإِنَّا لَهُۥ لَحَـٰفِظُونَ"},{"loc":"13:15","text":"وَلِلَّهِ يَسْجُدُ مَن فِى ٱلسَّمَـٰوَٰتِ وَٱلْأَرْضِ طَوْعًا وَكَرْهًا وَظِلَـٰلُهُم بِٱلْغُدُوِّ وَٱلْـَٔاصَالِ ۩"},{"loc":"18:28","text":"وَٱصْبِرْ نَفْسَكَ مَعَ ٱلَّذِينَ يَدْعُونَ رَبَّهُم بِٱلْغَدَوٰةِ وَٱلْعَشِىِّ يُرِيدُونَ وَجْهَهُۥ ۖ وَلَا تَعْدُ عَيْنَاكَ عَنْهُمْ تُرِيدُ زِينَةَ ٱلْحَيَوٰةِ ٱلدُّنْيَا ۖ وَلَا تُطِعْ مَنْ أَغْفَلْنَا قَلْبَهُۥ عَن ذِكْرِنَا وَٱتَّبَعَ هَوَىٰهُ وَكَانَ أَمْرُهُۥ فُرُطًا"},{"loc":"18:62","text":"فَلَمَّا جَاوَزَا قَالَ لِفَتَىٰهُ ءَاتِنَا غَدَآءَنَا لَقَدْ لَقِينَا مِن سَفَرِنَا هَـٰذَا نَصَبًا"},{"loc":"24:36","text":"فِى بُيُوتٍ أَذِنَ ٱللَّهُ أَن تُرْفَعَ وَيُذْكَرَ فِيهَا ٱسْمُهُۥ يُسَبِّحُ لَهُۥ فِيهَا بِٱلْغُدُوِّ وَٱلْـَٔاصَالِ"},{"loc":"31:34","text":"إِنَّ ٱللَّهَ عِندَهُۥ عِلْمُ ٱلسَّاعَةِ وَيُنَزِّلُ ٱلْغَيْثَ وَيَعْلَمُ مَا فِى ٱلْأَرْحَامِ ۖ وَمَا تَدْرِى نَفْسٌ مَّاذَا تَكْسِبُ غَدًا ۖ وَمَا تَدْرِى نَفْسٌۢ بِأَىِّ أَرْضٍ تَمُوتُ ۚ إِنَّ ٱللَّهَ عَلِيمٌ خَبِيرٌۢ"},{"loc":"34:12","text":"وَلِسُلَيْمَـٰنَ ٱلرِّيحَ غُدُوُّهَا شَهْرٌ وَرَوَاحُهَا شَهْرٌ ۖ وَأَسَلْنَا لَهُۥ عَيْنَ ٱلْقِطْرِ ۖ وَمِنَ ٱلْجِنِّ مَن يَعْمَلُ بَيْنَ يَدَيْهِ بِإِذْنِ رَبِّهِۦ ۖ وَمَن يَزِغْ مِنْهُمْ عَنْ أَمْرِنَا نُذِقْهُ مِنْ عَذَابِ ٱلسَّعِيرِ"}]},{"id":"68:41/aya","unit_text":"أَمْ لَهُمْ شُرَكَآءُ فَلْيَأْتُوا۟ بِشُرَكَآئِهِمْ إِن كَانُوا۟ صَـٰدِقِينَ","full_ayah":"أَمْ لَهُمْ شُرَكَآءُ فَلْيَأْتُوا۟ بِشُرَكَآئِهِمْ إِن كَانُوا۟ صَـٰدِقِينَ","gates":["G1h:لام-الأمر"],"candidates":[{"loc":"28:74","text":"وَيَوْمَ يُنَادِيهِمْ فَيَقُولُ أَيْنَ شُرَكَآءِىَ ٱلَّذِينَ كُنتُمْ تَزْعُمُونَ"},{"loc":"52:34","text":"فَلْيَأْتُوا۟ بِحَدِيثٍ مِّثْلِهِۦٓ إِن كَانُوا۟ صَـٰدِقِينَ"},{"loc":"28:62","text":"وَيَوْمَ يُنَادِيهِمْ فَيَقُولُ أَيْنَ شُرَكَآءِىَ ٱلَّذِينَ كُنتُمْ تَزْعُمُونَ"},{"loc":"37:157","text":"فَأْتُوا۟ بِكِتَـٰبِكُمْ إِن كُنتُمْ صَـٰدِقِينَ"},{"loc":"46:22","text":"قَالُوٓا۟ أَجِئْتَنَا لِتَأْفِكَنَا عَنْ ءَالِهَتِنَا فَأْتِنَا بِمَا تَعِدُنَآ إِن كُنتَ مِنَ ٱلصَّـٰدِقِينَ"},{"loc":"46:4","text":"قُلْ أَرَءَيْتُم مَّا تَدْعُونَ مِن دُونِ ٱللَّهِ أَرُونِى مَاذَا خَلَقُوا۟ مِنَ ٱلْأَرْضِ أَمْ لَهُمْ شِرْكٌ فِى ٱلسَّمَـٰوَٰتِ ۖ ٱئْتُونِى بِكِتَـٰبٍ مِّن قَبْلِ هَـٰذَآ أَوْ أَثَـٰرَةٍ مِّنْ عِلْمٍ إِن كُنتُمْ صَـٰدِقِينَ"},{"loc":"34:27","text":"قُلْ أَرُونِىَ ٱلَّذِينَ أَلْحَقْتُم بِهِۦ شُرَكَآءَ ۖ كَلَّا ۚ بَلْ هُوَ ٱللَّهُ ٱلْعَزِيزُ ٱلْحَكِيمُ"},{"loc":"10:35","text":"قُلْ هَلْ مِن شُرَكَآئِكُم مَّن يَهْدِىٓ إِلَى ٱلْحَقِّ ۚ قُلِ ٱللَّهُ يَهْدِى لِلْحَقِّ ۗ أَفَمَن يَهْدِىٓ إِلَى ٱلْحَقِّ أَحَقُّ أَن يُتَّبَعَ أَمَّن لَّا يَهِدِّىٓ إِلَّآ أَن يُهْدَىٰ ۖ فَمَا لَكُمْ كَيْفَ تَحْكُمُونَ"},{"loc":"35:40","text":"قُلْ أَرَءَيْتُمْ شُرَكَآءَكُمُ ٱلَّذِينَ تَدْعُونَ مِن دُونِ ٱللَّهِ أَرُونِى مَاذَا خَلَقُوا۟ مِنَ ٱلْأَرْضِ أَمْ لَهُمْ شِرْكٌ فِى ٱلسَّمَـٰوَٰتِ أَمْ ءَاتَيْنَـٰهُمْ كِتَـٰبًا فَهُمْ عَلَىٰ بَيِّنَتٍ مِّنْهُ ۚ بَلْ إِن يَعِدُ ٱلظَّـٰلِمُونَ بَعْضُهُم بَعْضًا إِلَّا غُرُورًا"},{"loc":"6:22","text":"وَيَوْمَ نَحْشُرُهُمْ جَمِيعًا ثُمَّ نَقُولُ لِلَّذِينَ أَشْرَكُوٓا۟ أَيْنَ شُرَكَآؤُكُمُ ٱلَّذِينَ كُنتُمْ تَزْعُمُونَ"},{"loc":"30:13","text":"وَلَمْ يَكُن لَّهُم مِّن شُرَكَآئِهِمْ شُفَعَـٰٓؤُا۟ وَكَانُوا۟ بِشُرَكَآئِهِمْ كَـٰفِرِينَ"},{"loc":"7:194","text":"إِنَّ ٱلَّذِينَ تَدْعُونَ مِن دُونِ ٱللَّهِ عِبَادٌ أَمْثَالُكُمْ ۖ فَٱدْعُوهُمْ فَلْيَسْتَجِيبُوا۟ لَكُمْ إِن كُنتُمْ صَـٰدِقِينَ"},{"loc":"16:86","text":"وَإِذَا رَءَا ٱلَّذِينَ أَشْرَكُوا۟ شُرَكَآءَهُمْ قَالُوا۟ رَبَّنَا هَـٰٓؤُلَآءِ شُرَكَآؤُنَا ٱلَّذِينَ كُنَّا نَدْعُوا۟ مِن دُونِكَ ۖ فَأَلْقَوْا۟ إِلَيْهِمُ ٱلْقَوْلَ إِنَّكُمْ لَكَـٰذِبُونَ"},{"loc":"21:43","text":"أَمْ لَهُمْ ءَالِهَةٌ تَمْنَعُهُم مِّن دُونِنَا ۚ لَا يَسْتَطِيعُونَ نَصْرَ أَنفُسِهِمْ وَلَا هُم مِّنَّا يُصْحَبُونَ"},{"loc":"7:70","text":"قَالُوٓا۟ أَجِئْتَنَا لِنَعْبُدَ ٱللَّهَ وَحْدَهُۥ وَنَذَرَ مَا كَانَ يَعْبُدُ ءَابَآؤُنَا ۖ فَأْتِنَا بِمَا تَعِدُنَآ إِن كُنتَ مِنَ ٱلصَّـٰدِقِينَ"},{"loc":"15:64","text":"وَأَتَيْنَـٰكَ بِٱلْحَقِّ وَإِنَّا لَصَـٰدِقُونَ"},{"loc":"52:43","text":"أَمْ لَهُمْ إِلَـٰهٌ غَيْرُ ٱللَّهِ ۚ سُبْحَـٰنَ ٱللَّهِ عَمَّا يُشْرِكُونَ"},{"loc":"21:24","text":"أَمِ ٱتَّخَذُوا۟ مِن دُونِهِۦٓ ءَالِهَةً ۖ قُلْ هَاتُوا۟ بُرْهَـٰنَكُمْ ۖ هَـٰذَا ذِكْرُ مَن مَّعِىَ وَذِكْرُ مَن قَبْلِى ۗ بَلْ أَكْثَرُهُمْ لَا يَعْلَمُونَ ٱلْحَقَّ ۖ فَهُم مُّعْرِضُونَ"},{"loc":"15:7","text":"لَّوْ مَا تَأْتِينَا بِٱلْمَلَـٰٓئِكَةِ إِن كُنتَ مِنَ ٱلصَّـٰدِقِينَ"},{"loc":"10:48","text":"وَيَقُولُونَ مَتَىٰ هَـٰذَا ٱلْوَعْدُ إِن كُنتُمْ صَـٰدِقِينَ"},{"loc":"44:36","text":"فَأْتُوا۟ بِـَٔابَآئِنَآ إِن كُنتُمْ صَـٰدِقِينَ"},{"loc":"52:38","text":"أَمْ لَهُمْ سُلَّمٌ يَسْتَمِعُونَ فِيهِ ۖ فَلْيَأْتِ مُسْتَمِعُهُم بِسُلْطَـٰنٍ مُّبِينٍ"},{"loc":"24:49","text":"وَإِن يَكُن لَّهُمُ ٱلْحَقُّ يَأْتُوٓا۟ إِلَيْهِ مُذْعِنِينَ"},{"loc":"7:195","text":"أَلَهُمْ أَرْجُلٌ يَمْشُونَ بِهَآ ۖ أَمْ لَهُمْ أَيْدٍ يَبْطِشُونَ بِهَآ ۖ أَمْ لَهُمْ أَعْيُنٌ يُبْصِرُونَ بِهَآ ۖ أَمْ لَهُمْ ءَاذَانٌ يَسْمَعُونَ بِهَا ۗ قُلِ ٱدْعُوا۟ شُرَكَآءَكُمْ ثُمَّ كِيدُونِ فَلَا تُنظِرُونِ"},{"loc":"56:87","text":"تَرْجِعُونَهَآ إِن كُنتُمْ صَـٰدِقِينَ"},{"loc":"96:17","text":"فَلْيَدْعُ نَادِيَهُۥ"},{"loc":"4:53","text":"أَمْ لَهُمْ نَصِيبٌ مِّنَ ٱلْمُلْكِ فَإِذًا لَّا يُؤْتُونَ ٱلنَّاسَ نَقِيرًا"},{"loc":"3:95","text":"قُلْ صَدَقَ ٱللَّهُ ۗ فَٱتَّبِعُوا۟ مِلَّةَ إِبْرَٰهِيمَ حَنِيفًا وَمَا كَانَ مِنَ ٱلْمُشْرِكِينَ"},{"loc":"2:96","text":"وَلَتَجِدَنَّهُمْ أَحْرَصَ ٱلنَّاسِ عَلَىٰ حَيَوٰةٍ وَمِنَ ٱلَّذِينَ أَشْرَكُوا۟ ۚ يَوَدُّ أَحَدُهُمْ لَوْ يُعَمَّرُ أَلْفَ سَنَةٍ وَمَا هُوَ بِمُزَحْزِحِهِۦ مِنَ ٱلْعَذَابِ أَن يُعَمَّرَ ۗ وَٱللَّهُ بَصِيرٌۢ بِمَا يَعْمَلُونَ"},{"loc":"2:105","text":"مَّا يَوَدُّ ٱلَّذِينَ كَفَرُوا۟ مِنْ أَهْلِ ٱلْكِتَـٰبِ وَلَا ٱلْمُشْرِكِينَ أَن يُنَزَّلَ عَلَيْكُم مِّنْ خَيْرٍ مِّن رَّبِّكُمْ ۗ وَٱللَّهُ يَخْتَصُّ بِرَحْمَتِهِۦ مَن يَشَآءُ ۚ وَٱللَّهُ ذُو ٱلْفَضْلِ ٱلْعَظِيمِ"},{"loc":"2:135","text":"وَقَالُوا۟ كُونُوا۟ هُودًا أَوْ نَصَـٰرَىٰ تَهْتَدُوا۟ ۗ قُلْ بَلْ مِلَّةَ إِبْرَٰهِـۧمَ حَنِيفًا ۖ وَمَا كَانَ مِنَ ٱلْمُشْرِكِينَ"},{"loc":"2:221","text":"وَلَا تَنكِحُوا۟ ٱلْمُشْرِكَـٰتِ حَتَّىٰ يُؤْمِنَّ ۚ وَلَأَمَةٌ مُّؤْمِنَةٌ خَيْرٌ مِّن مُّشْرِكَةٍ وَلَوْ أَعْجَبَتْكُمْ ۗ وَلَا تُنكِحُوا۟ ٱلْمُشْرِكِينَ حَتَّىٰ يُؤْمِنُوا۟ ۚ وَلَعَبْدٌ مُّؤْمِنٌ خَيْرٌ مِّن مُّشْرِكٍ وَلَوْ أَعْجَبَكُمْ ۗ أُو۟لَـٰٓئِكَ يَدْعُونَ إِلَى ٱلنَّارِ ۖ وَٱللَّهُ يَدْعُوٓا۟ إِلَى ٱلْجَنَّةِ وَٱلْمَغْفِرَةِ بِإِذْنِهِۦ ۖ وَيُبَيِّنُ ءَايَـٰتِهِۦ لِلنَّاسِ لَعَلَّهُمْ يَتَذَكَّرُونَ"}]},{"id":"68:52/aya","unit_text":"وَمَا هُوَ إِلَّا ذِكْرٌ لِّلْعَـٰلَمِينَ","full_ayah":"وَمَا هُوَ إِلَّا ذِكْرٌ لِّلْعَـٰلَمِينَ","gates":["G1c:نفي+نكرة","G1d:حصر-إلا"],"candidates":[{"loc":"12:104","text":"وَمَا تَسْـَٔلُهُمْ عَلَيْهِ مِنْ أَجْرٍ ۚ إِنْ هُوَ إِلَّا ذِكْرٌ لِّلْعَـٰلَمِينَ"},{"loc":"26:209","text":"ذِكْرَىٰ وَمَا كُنَّا ظَـٰلِمِينَ"},{"loc":"80:11","text":"كَلَّآ إِنَّهَا تَذْكِرَةٌ"},{"loc":"88:21","text":"فَذَكِّرْ إِنَّمَآ أَنتَ مُذَكِّرٌ"},{"loc":"40:54","text":"هُدًى وَذِكْرَىٰ لِأُو۟لِى ٱلْأَلْبَـٰبِ"},{"loc":"20:3","text":"إِلَّا تَذْكِرَةً لِّمَن يَخْشَىٰ"},{"loc":"74:54","text":"كَلَّآ إِنَّهُۥ تَذْكِرَةٌ"},{"loc":"43:44","text":"وَإِنَّهُۥ لَذِكْرٌ لَّكَ وَلِقَوْمِكَ ۖ وَسَوْفَ تُسْـَٔلُونَ"},{"loc":"87:9","text":"فَذَكِّرْ إِن نَّفَعَتِ ٱلذِّكْرَىٰ"},{"loc":"76:29","text":"إِنَّ هَـٰذِهِۦ تَذْكِرَةٌ ۖ فَمَن شَآءَ ٱتَّخَذَ إِلَىٰ رَبِّهِۦ سَبِيلًا"},{"loc":"69:48","text":"وَإِنَّهُۥ لَتَذْكِرَةٌ لِّلْمُتَّقِينَ"},{"loc":"73:19","text":"إِنَّ هَـٰذِهِۦ تَذْكِرَةٌ ۖ فَمَن شَآءَ ٱتَّخَذَ إِلَىٰ رَبِّهِۦ سَبِيلًا"},{"loc":"51:55","text":"وَذَكِّرْ فَإِنَّ ٱلذِّكْرَىٰ تَنفَعُ ٱلْمُؤْمِنِينَ"},{"loc":"38:49","text":"هَـٰذَا ذِكْرٌ ۚ وَإِنَّ لِلْمُتَّقِينَ لَحُسْنَ مَـَٔابٍ"},{"loc":"14:52","text":"هَـٰذَا بَلَـٰغٌ لِّلنَّاسِ وَلِيُنذَرُوا۟ بِهِۦ وَلِيَعْلَمُوٓا۟ أَنَّمَا هُوَ إِلَـٰهٌ وَٰحِدٌ وَلِيَذَّكَّرَ أُو۟لُوا۟ ٱلْأَلْبَـٰبِ"},{"loc":"26:192","text":"وَإِنَّهُۥ لَتَنزِيلُ رَبِّ ٱلْعَـٰلَمِينَ"},{"loc":"39:27","text":"وَلَقَدْ ضَرَبْنَا لِلنَّاسِ فِى هَـٰذَا ٱلْقُرْءَانِ مِن كُلِّ مَثَلٍ لَّعَلَّهُمْ يَتَذَكَّرُونَ"},{"loc":"36:70","text":"لِّيُنذِرَ مَن كَانَ حَيًّا وَيَحِقَّ ٱلْقَوْلُ عَلَى ٱلْكَـٰفِرِينَ"},{"loc":"56:73","text":"نَحْنُ جَعَلْنَـٰهَا تَذْكِرَةً وَمَتَـٰعًا لِّلْمُقْوِينَ"},{"loc":"50:8","text":"تَبْصِرَةً وَذِكْرَىٰ لِكُلِّ عَبْدٍ مُّنِيبٍ"},{"loc":"6:90","text":"أُو۟لَـٰٓئِكَ ٱلَّذِينَ هَدَى ٱللَّهُ ۖ فَبِهُدَىٰهُمُ ٱقْتَدِهْ ۗ قُل لَّآ أَسْـَٔلُكُمْ عَلَيْهِ أَجْرًا ۖ إِنْ هُوَ إِلَّا ذِكْرَىٰ لِلْعَـٰلَمِينَ"},{"loc":"80:12","text":"فَمَن شَآءَ ذَكَرَهُۥ"},{"loc":"86:14","text":"وَمَا هُوَ بِٱلْهَزْلِ"},{"loc":"2:40","text":"يَـٰبَنِىٓ إِسْرَٰٓءِيلَ ٱذْكُرُوا۟ نِعْمَتِىَ ٱلَّتِىٓ أَنْعَمْتُ عَلَيْكُمْ وَأَوْفُوا۟ بِعَهْدِىٓ أُوفِ بِعَهْدِكُمْ وَإِيَّـٰىَ فَٱرْهَبُونِ"},{"loc":"2:47","text":"يَـٰبَنِىٓ إِسْرَٰٓءِيلَ ٱذْكُرُوا۟ نِعْمَتِىَ ٱلَّتِىٓ أَنْعَمْتُ عَلَيْكُمْ وَأَنِّى فَضَّلْتُكُمْ عَلَى ٱلْعَـٰلَمِينَ"},{"loc":"2:63","text":"وَإِذْ أَخَذْنَا مِيثَـٰقَكُمْ وَرَفَعْنَا فَوْقَكُمُ ٱلطُّورَ خُذُوا۟ مَآ ءَاتَيْنَـٰكُم بِقُوَّةٍ وَٱذْكُرُوا۟ مَا فِيهِ لَعَلَّكُمْ تَتَّقُونَ"},{"loc":"2:114","text":"وَمَنْ أَظْلَمُ مِمَّن مَّنَعَ مَسَـٰجِدَ ٱللَّهِ أَن يُذْكَرَ فِيهَا ٱسْمُهُۥ وَسَعَىٰ فِى خَرَابِهَآ ۚ أُو۟لَـٰٓئِكَ مَا كَانَ لَهُمْ أَن يَدْخُلُوهَآ إِلَّا خَآئِفِينَ ۚ لَهُمْ فِى ٱلدُّنْيَا خِزْىٌ وَلَهُمْ فِى ٱلْـَٔاخِرَةِ عَذَابٌ عَظِيمٌ"},{"loc":"2:122","text":"يَـٰبَنِىٓ إِسْرَٰٓءِيلَ ٱذْكُرُوا۟ نِعْمَتِىَ ٱلَّتِىٓ أَنْعَمْتُ عَلَيْكُمْ وَأَنِّى فَضَّلْتُكُمْ عَلَى ٱلْعَـٰلَمِينَ"},{"loc":"2:152","text":"فَٱذْكُرُونِىٓ أَذْكُرْكُمْ وَٱشْكُرُوا۟ لِى وَلَا تَكْفُرُونِ"},{"loc":"2:198","text":"لَيْسَ عَلَيْكُمْ جُنَاحٌ أَن تَبْتَغُوا۟ فَضْلًا مِّن رَّبِّكُمْ ۚ فَإِذَآ أَفَضْتُم مِّنْ عَرَفَـٰتٍ فَٱذْكُرُوا۟ ٱللَّهَ عِندَ ٱلْمَشْعَرِ ٱلْحَرَامِ ۖ وَٱذْكُرُوهُ كَمَا هَدَىٰكُمْ وَإِن كُنتُم مِّن قَبْلِهِۦ لَمِنَ ٱلضَّآلِّينَ"},{"loc":"2:200","text":"فَإِذَا قَضَيْتُم مَّنَـٰسِكَكُمْ فَٱذْكُرُوا۟ ٱللَّهَ كَذِكْرِكُمْ ءَابَآءَكُمْ أَوْ أَشَدَّ ذِكْرًا ۗ فَمِنَ ٱلنَّاسِ مَن يَقُولُ رَبَّنَآ ءَاتِنَا فِى ٱلدُّنْيَا وَمَا لَهُۥ فِى ٱلْـَٔاخِرَةِ مِنْ خَلَـٰقٍ"},{"loc":"2:203","text":"۞ وَٱذْكُرُوا۟ ٱللَّهَ فِىٓ أَيَّامٍ مَّعْدُودَٰتٍ ۚ فَمَن تَعَجَّلَ فِى يَوْمَيْنِ فَلَآ إِثْمَ عَلَيْهِ وَمَن تَأَخَّرَ فَلَآ إِثْمَ عَلَيْهِ ۚ لِمَنِ ٱتَّقَىٰ ۗ وَٱتَّقُوا۟ ٱللَّهَ وَٱعْلَمُوٓا۟ أَنَّكُمْ إِلَيْهِ تُحْشَرُونَ"}]},{"id":"69:18/aya","unit_text":"يَوْمَئِذٍ تُعْرَضُونَ لَا تَخْفَىٰ مِنكُمْ خَافِيَةٌ","full_ayah":"يَوْمَئِذٍ تُعْرَضُونَ لَا تَخْفَىٰ مِنكُمْ خَافِيَةٌ","gates":["G1c:نفي+نكرة"],"candidates":[{"loc":"99:6","text":"يَوْمَئِذٍ يَصْدُرُ ٱلنَّاسُ أَشْتَاتًا لِّيُرَوْا۟ أَعْمَـٰلَهُمْ"},{"loc":"100:11","text":"إِنَّ رَبَّهُم بِهِمْ يَوْمَئِذٍ لَّخَبِيرٌۢ"},{"loc":"77:38","text":"هَـٰذَا يَوْمُ ٱلْفَصْلِ ۖ جَمَعْنَـٰكُمْ وَٱلْأَوَّلِينَ"},{"loc":"40:16","text":"يَوْمَ هُم بَـٰرِزُونَ ۖ لَا يَخْفَىٰ عَلَى ٱللَّهِ مِنْهُمْ شَىْءٌ ۚ لِّمَنِ ٱلْمُلْكُ ٱلْيَوْمَ ۖ لِلَّهِ ٱلْوَٰحِدِ ٱلْقَهَّارِ"},{"loc":"36:32","text":"وَإِن كُلٌّ لَّمَّا جَمِيعٌ لَّدَيْنَا مُحْضَرُونَ"},{"loc":"86:9","text":"يَوْمَ تُبْلَى ٱلسَّرَآئِرُ"},{"loc":"18:100","text":"وَعَرَضْنَا جَهَنَّمَ يَوْمَئِذٍ لِّلْكَـٰفِرِينَ عَرْضًا"},{"loc":"39:31","text":"ثُمَّ إِنَّكُمْ يَوْمَ ٱلْقِيَـٰمَةِ عِندَ رَبِّكُمْ تَخْتَصِمُونَ"},{"loc":"66:7","text":"يَـٰٓأَيُّهَا ٱلَّذِينَ كَفَرُوا۟ لَا تَعْتَذِرُوا۟ ٱلْيَوْمَ ۖ إِنَّمَا تُجْزَوْنَ مَا كُنتُمْ تَعْمَلُونَ"},{"loc":"16:111","text":"۞ يَوْمَ تَأْتِى كُلُّ نَفْسٍ تُجَـٰدِلُ عَن نَّفْسِهَا وَتُوَفَّىٰ كُلُّ نَفْسٍ مَّا عَمِلَتْ وَهُمْ لَا يُظْلَمُونَ"},{"loc":"58:6","text":"يَوْمَ يَبْعَثُهُمُ ٱللَّهُ جَمِيعًا فَيُنَبِّئُهُم بِمَا عَمِلُوٓا۟ ۚ أَحْصَىٰهُ ٱللَّهُ وَنَسُوهُ ۚ وَٱللَّهُ عَلَىٰ كُلِّ شَىْءٍ شَهِيدٌ"},{"loc":"37:21","text":"هَـٰذَا يَوْمُ ٱلْفَصْلِ ٱلَّذِى كُنتُم بِهِۦ تُكَذِّبُونَ"},{"loc":"83:15","text":"كَلَّآ إِنَّهُمْ عَن رَّبِّهِمْ يَوْمَئِذٍ لَّمَحْجُوبُونَ"},{"loc":"2:123","text":"وَٱتَّقُوا۟ يَوْمًا لَّا تَجْزِى نَفْسٌ عَن نَّفْسٍ شَيْـًٔا وَلَا يُقْبَلُ مِنْهَا عَدْلٌ وَلَا تَنفَعُهَا شَفَـٰعَةٌ وَلَا هُمْ يُنصَرُونَ"},{"loc":"10:30","text":"هُنَالِكَ تَبْلُوا۟ كُلُّ نَفْسٍ مَّآ أَسْلَفَتْ ۚ وَرُدُّوٓا۟ إِلَى ٱللَّهِ مَوْلَىٰهُمُ ٱلْحَقِّ ۖ وَضَلَّ عَنْهُم مَّا كَانُوا۟ يَفْتَرُونَ"},{"loc":"36:54","text":"فَٱلْيَوْمَ لَا تُظْلَمُ نَفْسٌ شَيْـًٔا وَلَا تُجْزَوْنَ إِلَّا مَا كُنتُمْ تَعْمَلُونَ"},{"loc":"75:30","text":"إِلَىٰ رَبِّكَ يَوْمَئِذٍ ٱلْمَسَاقُ"},{"loc":"3:25","text":"فَكَيْفَ إِذَا جَمَعْنَـٰهُمْ لِيَوْمٍ لَّا رَيْبَ فِيهِ وَوُفِّيَتْ كُلُّ نَفْسٍ مَّا كَسَبَتْ وَهُمْ لَا يُظْلَمُونَ"},{"loc":"24:24","text":"يَوْمَ تَشْهَدُ عَلَيْهِمْ أَلْسِنَتُهُمْ وَأَيْدِيهِمْ وَأَرْجُلُهُم بِمَا كَانُوا۟ يَعْمَلُونَ"},{"loc":"23:16","text":"ثُمَّ إِنَّكُمْ يَوْمَ ٱلْقِيَـٰمَةِ تُبْعَثُونَ"},{"loc":"80:37","text":"لِكُلِّ ٱمْرِئٍ مِّنْهُمْ يَوْمَئِذٍ شَأْنٌ يُغْنِيهِ"},{"loc":"55:39","text":"فَيَوْمَئِذٍ لَّا يُسْـَٔلُ عَن ذَنۢبِهِۦٓ إِنسٌ وَلَا جَآنٌّ"},{"loc":"88:2","text":"وُجُوهٌ يَوْمَئِذٍ خَـٰشِعَةٌ"},{"loc":"75:13","text":"يُنَبَّؤُا۟ ٱلْإِنسَـٰنُ يَوْمَئِذٍۭ بِمَا قَدَّمَ وَأَخَّرَ"},{"loc":"10:45","text":"وَيَوْمَ يَحْشُرُهُمْ كَأَن لَّمْ يَلْبَثُوٓا۟ إِلَّا سَاعَةً مِّنَ ٱلنَّهَارِ يَتَعَارَفُونَ بَيْنَهُمْ ۚ قَدْ خَسِرَ ٱلَّذِينَ كَذَّبُوا۟ بِلِقَآءِ ٱللَّهِ وَمَا كَانُوا۟ مُهْتَدِينَ"},{"loc":"18:47","text":"وَيَوْمَ نُسَيِّرُ ٱلْجِبَالَ وَتَرَى ٱلْأَرْضَ بَارِزَةً وَحَشَرْنَـٰهُمْ فَلَمْ نُغَادِرْ مِنْهُمْ أَحَدًا"},{"loc":"20:15","text":"إِنَّ ٱلسَّاعَةَ ءَاتِيَةٌ أَكَادُ أُخْفِيهَا لِتُجْزَىٰ كُلُّ نَفْسٍۭ بِمَا تَسْعَىٰ"},{"loc":"11:103","text":"إِنَّ فِى ذَٰلِكَ لَـَٔايَةً لِّمَنْ خَافَ عَذَابَ ٱلْـَٔاخِرَةِ ۚ ذَٰلِكَ يَوْمٌ مَّجْمُوعٌ لَّهُ ٱلنَّاسُ وَذَٰلِكَ يَوْمٌ مَّشْهُودٌ"},{"loc":"3:30","text":"يَوْمَ تَجِدُ كُلُّ نَفْسٍ مَّا عَمِلَتْ مِنْ خَيْرٍ مُّحْضَرًا وَمَا عَمِلَتْ مِن سُوٓءٍ تَوَدُّ لَوْ أَنَّ بَيْنَهَا وَبَيْنَهُۥٓ أَمَدًۢا بَعِيدًا ۗ وَيُحَذِّرُكُمُ ٱللَّهُ نَفْسَهُۥ ۗ وَٱللَّهُ رَءُوفٌۢ بِٱلْعِبَادِ"},{"loc":"28:66","text":"فَعَمِيَتْ عَلَيْهِمُ ٱلْأَنۢبَآءُ يَوْمَئِذٍ فَهُمْ لَا يَتَسَآءَلُونَ"},{"loc":"82:19","text":"يَوْمَ لَا تَمْلِكُ نَفْسٌ لِّنَفْسٍ شَيْـًٔا ۖ وَٱلْأَمْرُ يَوْمَئِذٍ لِّلَّهِ"},{"loc":"19:38","text":"أَسْمِعْ بِهِمْ وَأَبْصِرْ يَوْمَ يَأْتُونَنَا ۖ لَـٰكِنِ ٱلظَّـٰلِمُونَ ٱلْيَوْمَ فِى ضَلَـٰلٍ مُّبِينٍ"}]}]